{
"meta":{"test_sets":[],"test_metrics":[],"learn_metrics":[{"best_value":"Min","name":"RMSE"}],"launch_mode":"Train","parameters":"","iteration_count":100,"learn_sets":["learn"],"name":"experiment"},
"iterations":[
{"learn":[14.005006],"iteration":0,"passed_time":0.001006756225,"remaining_time":0.09966886625},
{"learn":[13.14441192],"iteration":1,"passed_time":0.001640276273,"remaining_time":0.08037353735},
{"learn":[12.34258257],"iteration":2,"passed_time":0.002250668498,"remaining_time":0.07277161478},
{"learn":[11.64527793],"iteration":3,"passed_time":0.002713094742,"remaining_time":0.0651142738},
{"learn":[11.02766183],"iteration":4,"passed_time":0.003376677407,"remaining_time":0.06415687074},
{"learn":[10.43485794],"iteration":5,"passed_time":0.004006414624,"remaining_time":0.06276716245},
{"learn":[9.890641275],"iteration":6,"passed_time":0.004536910522,"remaining_time":0.06027609694},
{"learn":[9.492161212],"iteration":7,"passed_time":0.005104378978,"remaining_time":0.05870035825},
{"learn":[9.105082953],"iteration":8,"passed_time":0.005733131428,"remaining_time":0.05796832888},
{"learn":[8.674157135],"iteration":9,"passed_time":0.01782568186,"remaining_time":0.1604311367},
{"learn":[8.341743544],"iteration":10,"passed_time":0.01862022789,"remaining_time":0.1506545711},
{"learn":[8.049372916],"iteration":11,"passed_time":0.01938391828,"remaining_time":0.142148734},
{"learn":[7.757318612],"iteration":12,"passed_time":0.02000149859,"remaining_time":0.1338561829},
{"learn":[7.522206899],"iteration":13,"passed_time":0.02076922866,"remaining_time":0.1275824046},
{"learn":[7.297756655],"iteration":14,"passed_time":0.02139186064,"remaining_time":0.1212205436},
{"learn":[7.088359431],"iteration":15,"passed_time":0.02183838384,"remaining_time":0.1146515152},
{"learn":[6.882113791],"iteration":16,"passed_time":0.02235014667,"remaining_time":0.1091213044},
{"learn":[6.704728832],"iteration":17,"passed_time":0.0227699202,"remaining_time":0.1037296364},
{"learn":[6.563881962],"iteration":18,"passed_time":0.02335221815,"remaining_time":0.09955419318},
{"learn":[6.418790279],"iteration":19,"passed_time":0.02393163875,"remaining_time":0.09572655498},
{"learn":[6.315756953],"iteration":20,"passed_time":0.0249187091,"remaining_time":0.09374181042},
{"learn":[6.210157751],"iteration":21,"passed_time":0.02559626551,"remaining_time":0.09075039591},
{"learn":[6.115058449],"iteration":22,"passed_time":0.02714637761,"remaining_time":0.09088135111},
{"learn":[6.014819884],"iteration":23,"passed_time":0.03797175419,"remaining_time":0.1202438883},
{"learn":[5.93117229],"iteration":24,"passed_time":0.0391953154,"remaining_time":0.1175859462},
{"learn":[5.844857622],"iteration":25,"passed_time":0.03982237765,"remaining_time":0.1133406133},
{"learn":[5.771145213],"iteration":26,"passed_time":0.04046292955,"remaining_time":0.1093997725},
{"learn":[5.704018229],"iteration":27,"passed_time":0.04110680622,"remaining_time":0.105703216},
{"learn":[5.665806474],"iteration":28,"passed_time":0.04181389736,"remaining_time":0.1023719556},
{"learn":[5.616500369],"iteration":29,"passed_time":0.04235634421,"remaining_time":0.09883146983},
{"learn":[5.558023666],"iteration":30,"passed_time":0.04293105402,"remaining_time":0.09555621701},
{"learn":[5.510080976],"iteration":31,"passed_time":0.04351675724,"remaining_time":0.09247310913},
{"learn":[5.468747792],"iteration":32,"passed_time":0.04413496309,"remaining_time":0.08960734931},
{"learn":[5.429275534],"iteration":33,"passed_time":0.04474900085,"remaining_time":0.08686570753},
{"learn":[5.402117324],"iteration":34,"passed_time":0.04527501203,"remaining_time":0.0840821652},
{"learn":[5.367635151],"iteration":35,"passed_time":0.0460759697,"remaining_time":0.08191283502},
{"learn":[5.345181232],"iteration":36,"passed_time":0.04738239101,"remaining_time":0.08067812523},
{"learn":[5.319151269],"iteration":37,"passed_time":0.04833739784,"remaining_time":0.07886628069},
{"learn":[5.296134146],"iteration":38,"passed_time":0.04926159994,"remaining_time":0.07705019477},
{"learn":[5.269629003],"iteration":39,"passed_time":0.05027918327,"remaining_time":0.07541877491},
{"learn":[5.251147059],"iteration":40,"passed_time":0.05680760167,"remaining_time":0.08174752436},
{"learn":[5.248003302],"iteration":41,"passed_time":0.05722836824,"remaining_time":0.07902965139},
{"learn":[5.232376509],"iteration":42,"passed_time":0.05783452905,"remaining_time":0.07666437572},
{"learn":[5.213524255],"iteration":43,"passed_time":0.05829893666,"remaining_time":0.07419864666},
{"learn":[5.189691584],"iteration":44,"passed_time":0.05884433426,"remaining_time":0.07192085299},
{"learn":[5.166052198],"iteration":45,"passed_time":0.05939842551,"remaining_time":0.06972858647},
{"learn":[5.140406659],"iteration":46,"passed_time":0.06007380171,"remaining_time":0.06774279767},
{"learn":[5.118929684],"iteration":47,"passed_time":0.06080496401,"remaining_time":0.06587204435},
{"learn":[5.108792602],"iteration":48,"passed_time":0.06148367682,"remaining_time":0.06399321465},
{"learn":[5.098141225],"iteration":49,"passed_time":0.06201162913,"remaining_time":0.06201162913},
{"learn":[5.085926393],"iteration":50,"passed_time":0.06268089433,"remaining_time":0.06022282004},
{"learn":[5.067816804],"iteration":51,"passed_time":0.06323181586,"remaining_time":0.05836783002},
{"learn":[5.049834901],"iteration":52,"passed_time":0.06377982569,"remaining_time":0.05655946807},
{"learn":[5.03838627],"iteration":53,"passed_time":0.06448010395,"remaining_time":0.05492749596},
{"learn":[5.033534248],"iteration":54,"passed_time":0.06480446041,"remaining_time":0.05302183125},
{"learn":[5.023726885],"iteration":55,"passed_time":0.06552500451,"remaining_time":0.05148393212},
{"learn":[5.01290392],"iteration":56,"passed_time":0.066521268,"remaining_time":0.05018271095},
{"learn":[5.005569127],"iteration":57,"passed_time":0.06786881753,"remaining_time":0.04914638511},
{"learn":[4.989969032],"iteration":58,"passed_time":0.06955932817,"remaining_time":0.04833783822},
{"learn":[4.976762446],"iteration":59,"passed_time":0.07015071273,"remaining_time":0.04676714182},
{"learn":[4.967222715],"iteration":60,"passed_time":0.07071761601,"remaining_time":0.04521290204},
{"learn":[4.954407599],"iteration":61,"passed_time":0.0714763589,"remaining_time":0.04380809094},
{"learn":[4.942125056],"iteration":62,"passed_time":0.07199181342,"remaining_time":0.0422809063},
{"learn":[4.930230716],"iteration":63,"passed_time":0.07250901497,"remaining_time":0.04078632092},
{"learn":[4.921695642],"iteration":64,"passed_time":0.07295386099,"remaining_time":0.03928284822},
{"learn":[4.906405625],"iteration":65,"passed_time":0.07352909395,"remaining_time":0.03787862416},
{"learn":[4.894330248],"iteration":66,"passed_time":0.07442709379,"remaining_time":0.03665812082},
{"learn":[4.88211557],"iteration":67,"passed_time":0.07611938694,"remaining_time":0.03582088797},
{"learn":[4.877946398],"iteration":68,"passed_time":0.07710050786,"remaining_time":0.0346393586},
{"learn":[4.863182126],"iteration":69,"passed_time":0.07784518112,"remaining_time":0.03336222048},
{"learn":[4.84646533],"iteration":70,"passed_time":0.07835942126,"remaining_time":0.0320059608},
{"learn":[4.838014752],"iteration":71,"passed_time":0.0788885631,"remaining_time":0.03067888565},
{"learn":[4.82981137],"iteration":72,"passed_time":0.08336028903,"remaining_time":0.03083188772},
{"learn":[4.817094767],"iteration":73,"passed_time":0.08491596056,"remaining_time":0.02983533749},
{"learn":[4.808314151],"iteration":74,"passed_time":0.08571292353,"remaining_time":0.02857097451},
{"learn":[4.796235023],"iteration":75,"passed_time":0.08716937978,"remaining_time":0.02752717256},
{"learn":[4.784434534],"iteration":76,"passed_time":0.09102566891,"remaining_time":0.02718948552},
{"learn":[4.774402487],"iteration":77,"passed_time":0.09378222597,"remaining_time":0.02645139707},
{"learn":[4.76731896],"iteration":78,"passed_time":0.09524843461,"remaining_time":0.02531920414},
{"learn":[4.75934113],"iteration":79,"passed_time":0.09649274458,"remaining_time":0.02412318614},
{"learn":[4.754106378],"iteration":80,"passed_time":0.09759250388,"remaining_time":0.02289206881},
{"learn":[4.744002932],"iteration":81,"passed_time":0.09962549389,"remaining_time":0.02186901085},
{"learn":[4.731700554],"iteration":82,"passed_time":0.1013571002,"remaining_time":0.02075988799},
{"learn":[4.723284153],"iteration":83,"passed_time":0.1029985974,"remaining_time":0.01961878045},
{"learn":[4.712232782],"iteration":84,"passed_time":0.1041681899,"remaining_time":0.01838262175},
{"learn":[4.703046867],"iteration":85,"passed_time":0.1050290172,"remaining_time":0.01709774698},
{"learn":[4.698601855],"iteration":86,"passed_time":0.1058061309,"remaining_time":0.01581011152},
{"learn":[4.692429407],"iteration":87,"passed_time":0.1064027447,"remaining_time":0.01450946518},
{"learn":[4.675027364],"iteration":88,"passed_time":0.1070888539,"remaining_time":0.01323570104},
{"learn":[4.662368584],"iteration":89,"passed_time":0.1076488348,"remaining_time":0.01196098165},
{"learn":[4.646206172],"iteration":90,"passed_time":0.1083707791,"remaining_time":0.01071798914},
{"learn":[4.641245848],"iteration":91,"passed_time":0.1088809962,"remaining_time":0.00946791271},
{"learn":[4.633900435],"iteration":92,"passed_time":0.1094849495,"remaining_time":0.008240802653},
{"learn":[4.624738236],"iteration":93,"passed_time":0.110022759,"remaining_time":0.007022729296},
{"learn":[4.612798287],"iteration":94,"passed_time":0.1106661658,"remaining_time":0.00582453504},
{"learn":[4.605222001],"iteration":95,"passed_time":0.1112770551,"remaining_time":0.004636543962},
{"learn":[4.601725912],"iteration":96,"passed_time":0.1117721621,"remaining_time":0.003456870993},
{"learn":[4.59722371],"iteration":97,"passed_time":0.1123642,"remaining_time":0.00229314694},
{"learn":[4.580235665],"iteration":98,"passed_time":0.1128978136,"remaining_time":0.001140381955},
{"learn":[4.57591791],"iteration":99,"passed_time":0.1214065198,"remaining_time":0}
]}